jiphy/__init__.py
jiphy/handlers.py
jiphy/main.py
jiphy/parser.py
jiphy/pie_slice.py
jiphy/router.py
jiphy/to.py
jiphy-1.2.1.dist-info/DESCRIPTION.rst
jiphy-1.2.1.dist-info/METADATA
jiphy-1.2.1.dist-info/RECORD
jiphy-1.2.1.dist-info/WHEEL
jiphy-1.2.1.dist-info/entry_points.txt
jiphy-1.2.1.dist-info/metadata.json
jiphy-1.2.1.dist-info/top_level.txt
