Metadata-Version: 1.1
Name: jiphy
Version: 1.2.1
Summary: A Python to JavaScript two way converter. Your client side done in a Jiphy.
Home-page: https://github.com/timothycrosley/jiphy
Author: Timothy Crosley
Author-email: timothy.crosley@gmail.com
License: MIT
Keywords: Refactor,Python,Python2,Python3,Refactoring,JavaScript,Converter,Transform,Convert
Platform: UNKNOWN
Classifier: Development Status :: 6 - Mature
Classifier: Intended Audience :: Developers
Classifier: Natural Language :: English
Classifier: Environment :: Console
Classifier: License :: OSI Approved :: MIT License
Classifier: Programming Language :: Python
Classifier: Programming Language :: Python :: 2
Classifier: Programming Language :: Python :: 2.6
Classifier: Programming Language :: Python :: 2.7
Classifier: Programming Language :: Python :: 3
Classifier: Programming Language :: Python :: 3.0
Classifier: Programming Language :: Python :: 3.1
Classifier: Programming Language :: Python :: 3.2
Classifier: Programming Language :: Python :: 3.3
Classifier: Programming Language :: Python :: 3.4
Classifier: Topic :: Software Development :: Libraries
Classifier: Topic :: Utilities
